odoo/addons/purchase_order_line_description_picking/README.rst
odoo/addons/purchase_order_line_description_picking/__init__.py
odoo/addons/purchase_order_line_description_picking/__manifest__.py
odoo/addons/purchase_order_line_description_picking/i18n/it.po
odoo/addons/purchase_order_line_description_picking/i18n/purchase_order_line_description_picking.pot
odoo/addons/purchase_order_line_description_picking/models/__init__.py
odoo/addons/purchase_order_line_description_picking/models/purchase_order_line.py
odoo/addons/purchase_order_line_description_picking/readme/CONTRIBUTORS.rst
odoo/addons/purchase_order_line_description_picking/readme/DESCRIPTION.rst
odoo/addons/purchase_order_line_description_picking/readme/USAGE.rst
odoo/addons/purchase_order_line_description_picking/static/description/icon.png
odoo/addons/purchase_order_line_description_picking/static/description/index.html
odoo/addons/purchase_order_line_description_picking/tests/__init__.py
odoo/addons/purchase_order_line_description_picking/tests/test_purchase_order_line_description_picking.py
odoo14_addon_purchase_order_line_description_picking-14.0.1.0.1.dev6.dist-info/METADATA
odoo14_addon_purchase_order_line_description_picking-14.0.1.0.1.dev6.dist-info/WHEEL
odoo14_addon_purchase_order_line_description_picking-14.0.1.0.1.dev6.dist-info/top_level.txt
odoo14_addon_purchase_order_line_description_picking-14.0.1.0.1.dev6.dist-info/RECORD
